LICENSE
README.md
setup.py
caterpillar_common/__init__.py
caterpillar_common.egg-info/PKG-INFO
caterpillar_common.egg-info/SOURCES.txt
caterpillar_common.egg-info/dependency_links.txt
caterpillar_common.egg-info/requires.txt
caterpillar_common.egg-info/top_level.txt
caterpillar_common/common/__init__.py
caterpillar_common/common/csv_utils.py
caterpillar_common/common/excel.py
caterpillar_common/common/log.py
caterpillar_common/logs/__init__.py
tests/common/__init__.py
tests/common/test_log.py